{"connections": [{"connectionId": "con_11", "pageSourceId": "breweries", "pageTargetId": "buffets"}, {"connectionId": "con_24", "pageSourceId": "breweries", "pageTargetId": "steakhouse"}, {"connectionId": "con_36", "pageSourceId": "bakeries", "pageTargetId": "dance_clubs"}, {"connectionId": "con_49", "pageSourceId": "bakeries", "pageTargetId": "juice_bars_and_smooties"}, {"connectionId": "con_60", "pageSourceId": "sports_bars", "pageTargetId": "bakeries"}, {"connectionId": "con_72", "pageSourceId": "bars", "pageTargetId": "bakeries"}, {"connectionId": "con_84", "pageSourceId": "dive_bars", "pageTargetId": "bakeries"}, {"connectionId": "con_97", "pageSourceId": "dive_bars", "pageTargetId": "cafes"}, {"connectionId": "con_108", "pageSourceId": "sports_bars", "pageTargetId": "cafes"}, {"connectionId": "con_119", "pageSourceId": "bars", "pageTargetId": "cafes"}, {"connectionId": "con_130", "pageSourceId": "pubs", "pageTargetId": "buffets"}, {"connectionId": "con_142", "pageSourceId": "pubs", "pageTargetId": "steakhouse"}, {"connectionId": "con_153", "pageSourceId": "sushi_bars", "pageTargetId": "steakhouse"}, {"connectionId": "con_165", "pageSourceId": "sushi_bars", "pageTargetId": "buffets"}, {"connectionId": "con_176", "pageSourceId": "lounges", "pageTargetId": "sports_bars"}, {"connectionId": "con_188", "pageSourceId": "lounges", "pageTargetId": "bars"}, {"connectionId": "con_199", "pageSourceId": "wine_bars", "pageTargetId": "bars"}, {"connectionId": "con_211", "pageSourceId": "wine_bars", "pageTargetId": "sports_bars"}, {"connectionId": "con_222", "pageSourceId": "wine_bars", "pageTargetId": "dive_bars"}], "message": "<p>Please specify the preference order for the TYPE of PLACE during DINNER.</p><p>Pease do not create loops. Click on a relation to delete it.</p>", "id": "0", "block": [{"positionY": 472, "positionX": 636, "blockId": "bakeries"}, {"positionY": 320, "positionX": 806, "blockId": "bars"}, {"positionY": 292, "positionX": 411, "blockId": "dive_bars"}, {"positionY": 106, "positionX": 232, "blockId": "pubs"}, {"positionY": 335, "positionX": 623, "blockId": "sports_bars"}, {"positionY": 120, "positionX": 407, "blockId": "sushi_bars"}, {"positionY": 117, "positionX": 54, "blockId": "breweries"}, {"positionY": 283, "positionX": 29, "blockId": "buffets"}, {"positionY": 410, "positionX": 460, "blockId": "cafes"}, {"positionY": 519, "positionX": 252, "blockId": "dance_clubs"}, {"positionY": 548, "positionX": 562, "blockId": "juice_bars_and_smooties"}, {"positionY": 116, "positionX": 558, "blockId": "lounges"}, {"positionY": 362, "positionX": 160, "blockId": "steakhouse"}, {"positionY": 106, "positionX": 750, "blockId": "wine_bars"}], "name": "0"}